google_drive_client
