Metadata-Version: 2.1
Name: google-drive-client
Version: 0.1.2
Summary: Google Drive Client package
Home-page: https://github.com/turisesonia/google_drive_client
Author: Sam Yao
Author-email: turisesonia@gmail.com
License: UNKNOWN
Platform: UNKNOWN
Classifier: Programming Language :: Python :: 3
Classifier: License :: OSI Approved :: MIT License
Classifier: Operating System :: OS Independent
Requires-Python: >=3.5
